{
  "case_id": "high_risk_mft_20251105_144121",
  "regime_type": "high_risk",
  "agent_type": "mft",
  "strategy_params": "<saved in .pkl file>",
  "sharpe_ratio": -4.888173350845528,
  "total_return": -47.312042288468405,
  "max_drawdown": -48.97190465454077,
  "win_rate": 0.36065573770491804,
  "market_volatility": 0.6217864597503604,
  "market_trend": -0.0008931868888388377,
  "market_correlation": 0.5,
  "training_episodes": 500,
  "timestamp": "2025-11-05T14:41:21.400585",
  "success_score": -6.822264785116711
}