{
  "case_id": "high_risk_lft_20251105_143654",
  "regime_type": "high_risk",
  "agent_type": "lft",
  "strategy_params": "<saved in .pkl file>",
  "sharpe_ratio": 0.26025349216125626,
  "total_return": 0.7491740747268327,
  "max_drawdown": -28.80271803824917,
  "win_rate": 0.45901639344262296,
  "market_volatility": 0.6217864597503604,
  "market_trend": -0.0008931868888388377,
  "market_correlation": 0.5,
  "training_episodes": 500,
  "timestamp": "2025-11-05T14:36:54.930878",
  "success_score": -2.5821196060477094
}