{
  "case_id": "high_return_hft_20251105_144315",
  "regime_type": "high_return",
  "agent_type": "hft",
  "strategy_params": "<saved in .pkl file>",
  "sharpe_ratio": 3.888093435081947,
  "total_return": 123.69920502914833,
  "max_drawdown": -5.6123387005284755,
  "win_rate": 0.6104513064133017,
  "market_volatility": 0.15723075723797608,
  "market_trend": 0.00129685539390861,
  "market_correlation": 0.5,
  "training_episodes": 500,
  "timestamp": "2025-11-05T14:43:15.279501",
  "success_score": 1.5871913803500368
}